qrgc/__init__.py
qrgc-0.0.3.dist-info/LICENSE
qrgc-0.0.3.dist-info/METADATA
qrgc-0.0.3.dist-info/WHEEL
qrgc-0.0.3.dist-info/top_level.txt
qrgc-0.0.3.dist-info/RECORD
