Metadata-Version: 2.1
Name: qrgc
Version: 0.0.3
Summary: Very basic library for QR code generator
Home-page: https://github.com/JosephFrankFir/QR-code-generator
Author: JosephFrankFir 
Author-email: josephfir@protonmail.com
License: UNKNOWN
Project-URL: Bug Tracker, https://github.com/JosephFrankFir/QR-code-generator/issues
Keywords: QR code
Platform: UNKNOWN
Classifier: Programming Language :: Python :: 3
Classifier: License :: OSI Approved :: GNU General Public License v3 (GPLv3)
Classifier: Operating System :: OS Independent
Requires-Python: >=3.6
License-File: LICENSE
